airavata_custos_portal/__init__.py
airavata_custos_portal/asgi.py
airavata_custos_portal/settings.py
airavata_custos_portal/urls.py
airavata_custos_portal/wsgi.py
airavata_custos_portal/apps/__init__.py
airavata_custos_portal/apps/api/__init__.py
airavata_custos_portal/apps/api/admin.py
airavata_custos_portal/apps/api/apps.py
airavata_custos_portal/apps/api/models.py
airavata_custos_portal/apps/api/tests.py
airavata_custos_portal/apps/api/urls.py
airavata_custos_portal/apps/api/views.py
airavata_custos_portal/apps/frontend/__init__.py
airavata_custos_portal/apps/frontend/admin.py
airavata_custos_portal/apps/frontend/apps.py
airavata_custos_portal/apps/frontend/models.py
airavata_custos_portal/apps/frontend/tests.py
airavata_custos_portal/apps/frontend/urls.py
airavata_custos_portal/apps/frontend/views.py
airavata_custos_portal/apps/frontend/static/airavata_custos_portal_frontend/dist/custos-logo_custos-logomark-color.png
airavata_custos_portal/apps/frontend/static/airavata_custos_portal_frontend/dist/favicon.ico
airavata_custos_portal/apps/frontend/static/airavata_custos_portal_frontend/dist/index.html
airavata_custos_portal/apps/frontend/static/airavata_custos_portal_frontend/dist/webpack-stats.json
airavata_custos_portal/apps/frontend/static/airavata_custos_portal_frontend/dist/css/account.a73855a0.css
airavata_custos_portal/apps/frontend/static/airavata_custos_portal_frontend/dist/css/app.d760f13b.css
airavata_custos_portal/apps/frontend/static/airavata_custos_portal_frontend/dist/css/chunk-vendors.e42a3c01.css
airavata_custos_portal/apps/frontend/static/airavata_custos_portal_frontend/dist/img/custos_home.0418730c.png
airavata_custos_portal/apps/frontend/static/airavata_custos_portal_frontend/dist/img/green-successfull-icon.dbeb8492.svg
airavata_custos_portal/apps/frontend/static/airavata_custos_portal_frontend/dist/img/not-found-icon.91cf4e27.svg
airavata_custos_portal/apps/frontend/static/airavata_custos_portal_frontend/dist/js/account.155becfb.js
airavata_custos_portal-0.0.6.dist-info/LICENSE
airavata_custos_portal-0.0.6.dist-info/METADATA
airavata_custos_portal-0.0.6.dist-info/WHEEL
airavata_custos_portal-0.0.6.dist-info/top_level.txt
airavata_custos_portal-0.0.6.dist-info/RECORD
