Metadata-Version: 2.1
Name: airavata-custos-portal
Version: 0.0.6
Summary: The Airavata Custos Portal SDK is a library that makes it easier to develop Airavata Custos Portal customizations.
Home-page: https://github.com/apache/airavata-custos-portal
Author: Apache Software Foundation
Author-email: dev@airavata.apache.org
License: Apache License 2.0
Classifier: Development Status :: 4 - Beta
Classifier: Environment :: Web Environment
Classifier: Framework :: Django
Classifier: Intended Audience :: Developers
Classifier: License :: OSI Approved :: Apache Software License
Classifier: Natural Language :: English
Classifier: Programming Language :: Python :: 3.6
Classifier: Topic :: Internet :: WWW/HTTP
Classifier: Topic :: Internet :: WWW/HTTP :: WSGI :: Application
License-File: LICENSE
Requires-Dist: Django (==3.2.16)
Requires-Dist: django-webpack-loader (==0.6.0)
Requires-Dist: djangorestframework (==3.14.0)
Requires-Dist: requests (==2.28.2)
Requires-Dist: PyJWT (==0.4.3)
Requires-Dist: django-environ
